darcpy/__init__.py
darcpy/darcpy.py
darcpy-0.0.0.dist-info/LICENSE
darcpy-0.0.0.dist-info/METADATA
darcpy-0.0.0.dist-info/WHEEL
darcpy-0.0.0.dist-info/top_level.txt
darcpy-0.0.0.dist-info/RECORD
